apiai_assistant/__init__.py
apiai_assistant/agent.py
apiai_assistant/assistant.py
apiai_assistant/corpus.py
apiai_assistant/parser.py
apiai_assistant/utils.py
apiai_assistant-0.1.1.dist-info/DESCRIPTION.rst
apiai_assistant-0.1.1.dist-info/METADATA
apiai_assistant-0.1.1.dist-info/RECORD
apiai_assistant-0.1.1.dist-info/WHEEL
apiai_assistant-0.1.1.dist-info/metadata.json
apiai_assistant-0.1.1.dist-info/top_level.txt
