Metadata-Version: 2.0
Name: apiai-assistant
Version: 0.1.1
Summary: Create API.ai agents in a heartbeat
Home-page: https://github.com/toasterco/apiai_assistant
Author: Toaster LTD developers
Author-email: developers@toasterltd.com
License: MIT
Keywords: apiai actionsongoogle alexa messenger voice home
Platform: any
Classifier: Development Status :: 3 - Alpha
Classifier: Intended Audience :: Developers
Classifier: Topic :: Software Development :: Quality Assurance
Classifier: License :: OSI Approved :: MIT License
Classifier: Natural Language :: English
Classifier: Programming Language :: Python :: 2
Classifier: Programming Language :: Python :: 2.6
Classifier: Programming Language :: Python :: 2.7
Classifier: Programming Language :: Python :: 3
Classifier: Programming Language :: Python :: 3.3
Classifier: Programming Language :: Python :: 3.4
Classifier: Programming Language :: Python :: 3.5
Classifier: Topic :: Communications :: Chat
Classifier: Topic :: Adaptive Technologies
Classifier: Topic :: Home Automation
Classifier: Topic :: Scientific/Engineering :: Artificial Intelligence
Classifier: Topic :: Scientific/Engineering :: Human Machine Interfaces
